newton/__init__.py
newton/_version.py
newton/geometry.py
newton/ik.py
newton/py.typed
newton/selection.py
newton/sensors.py
newton/solvers.py
newton/utils.py
newton/viewer.py
newton/_src/core/__init__.py
newton/_src/core/spatial.py
newton/_src/core/types.py
newton/_src/geometry/__init__.py
newton/_src/geometry/broad_phase_common.py
newton/_src/geometry/broad_phase_nxn.py
newton/_src/geometry/broad_phase_sap.py
newton/_src/geometry/collision_primitive.py
newton/_src/geometry/flags.py
newton/_src/geometry/gjk.py
newton/_src/geometry/inertia.py
newton/_src/geometry/kernels.py
newton/_src/geometry/raycast.py
newton/_src/geometry/types.py
newton/_src/geometry/utils.py
newton/_src/sensors/__init__.py
newton/_src/sensors/contact_sensor.py
newton/_src/sensors/raycast_sensor.py
newton/_src/sim/__init__.py
newton/_src/sim/articulation.py
newton/_src/sim/builder.py
newton/_src/sim/collide.py
newton/_src/sim/contacts.py
newton/_src/sim/control.py
newton/_src/sim/graph_coloring.py
newton/_src/sim/ik.py
newton/_src/sim/joints.py
newton/_src/sim/model.py
newton/_src/sim/sew.py
newton/_src/sim/state.py
newton/_src/sim/style3d/__init__.py
newton/_src/sim/style3d/builder_style3d.py
newton/_src/sim/style3d/model_style3d.py
newton/_src/solvers/__init__.py
newton/_src/solvers/flags.py
newton/_src/solvers/solver.py
newton/_src/solvers/euler/__init__.py
newton/_src/solvers/euler/kernels.py
newton/_src/solvers/euler/particles.py
newton/_src/solvers/euler/solver_euler.py
newton/_src/solvers/featherstone/__init__.py
newton/_src/solvers/featherstone/kernels.py
newton/_src/solvers/featherstone/solver_featherstone.py
newton/_src/solvers/implicit_mpm/__init__.py
newton/_src/solvers/implicit_mpm/rasterized_collisions.py
newton/_src/solvers/implicit_mpm/render_grains.py
newton/_src/solvers/implicit_mpm/solve_rheology.py
newton/_src/solvers/implicit_mpm/solver_implicit_mpm.py
newton/_src/solvers/mujoco/__init__.py
newton/_src/solvers/mujoco/solver_mujoco.py
newton/_src/solvers/style3d/__init__.py
newton-0.1.3.dist-info/METADATA
newton-0.1.3.dist-info/WHEEL
newton-0.1.3.dist-info/licenses/LICENSE.md
newton-0.1.3.dist-info/RECORD
