Metadata-Version: 2.4
Name: newton
Version: 0.1.3
Summary: A GPU-accelerated physics engine for robotics simulation
Author-email: Newton Developers <warp-python@nvidia.com>
License-Expression: Apache-2.0
License-File: LICENSE.md
Classifier: Development Status :: 2 - Pre-Alpha
Classifier: Environment :: GPU :: NVIDIA CUDA
Classifier: Environment :: GPU :: NVIDIA CUDA :: 12
Classifier: Intended Audience :: Developers
Classifier: Intended Audience :: Science/Research
Classifier: Natural Language :: English
Classifier: Programming Language :: Python :: 3
Classifier: Programming Language :: Python :: 3 :: Only
Classifier: Programming Language :: Python :: 3.10
Classifier: Programming Language :: Python :: 3.11
Classifier: Programming Language :: Python :: 3.12
Classifier: Topic :: Scientific/Engineering
Requires-Python: >=3.10
Requires-Dist: warp-lang>=1.7.0.dev20250823
Provides-Extra: dev
Requires-Dist: alphashape>=1.3.1; extra == 'dev'
Requires-Dist: cbor2>=5.7.0; extra == 'dev'
Requires-Dist: coacd>=1.0.7; extra == 'dev'
Requires-Dist: coverage[toml]>=7.8.0; extra == 'dev'
Requires-Dist: fast-simplification>=0.1.11; extra == 'dev'
Requires-Dist: gitpython>=3.1.44; extra == 'dev'
Requires-Dist: imgui-bundle>=1.92.0; extra == 'dev'
Requires-Dist: mujoco-warp>=0.0.1; extra == 'dev'
Requires-Dist: mujoco>=3.3.3.dev769049331; extra == 'dev'
Requires-Dist: pycollada>=0.9; extra == 'dev'
Requires-Dist: pyglet>=2.1.6; extra == 'dev'
Requires-Dist: pyyaml>=6.0.2; extra == 'dev'
Requires-Dist: scipy; extra == 'dev'
Requires-Dist: tqdm>=4.67.1; extra == 'dev'
Requires-Dist: trimesh>=4.6.8; extra == 'dev'
Requires-Dist: usd-core>=25.5; (platform_machine != 'aarch64') and extra == 'dev'
Requires-Dist: usd-exchange>=2.1.0a3; (platform_machine == 'aarch64') and extra == 'dev'
Provides-Extra: docs
Requires-Dist: myst-parser>=3.0.1; extra == 'docs'
Requires-Dist: pydata-sphinx-theme>=0.16.1; extra == 'docs'
Requires-Dist: sphinx-copybutton>=0.5.0; extra == 'docs'
Requires-Dist: sphinx-design<=0.6.1; extra == 'docs'
Requires-Dist: sphinx-tabs>=3.3.0; extra == 'docs'
Requires-Dist: sphinx>=7.4.7; extra == 'docs'
Requires-Dist: sphinxcontrib-mermaid>=1.0.0; extra == 'docs'
Provides-Extra: examples
Requires-Dist: alphashape>=1.3.1; extra == 'examples'
Requires-Dist: cbor2>=5.7.0; extra == 'examples'
Requires-Dist: coacd>=1.0.7; extra == 'examples'
Requires-Dist: fast-simplification>=0.1.11; extra == 'examples'
Requires-Dist: gitpython>=3.1.44; extra == 'examples'
Requires-Dist: imgui-bundle>=1.92.0; extra == 'examples'
Requires-Dist: mujoco-warp>=0.0.1; extra == 'examples'
Requires-Dist: mujoco>=3.3.3.dev769049331; extra == 'examples'
Requires-Dist: pycollada>=0.9; extra == 'examples'
Requires-Dist: pyglet>=2.1.6; extra == 'examples'
Requires-Dist: pyyaml>=6.0.2; extra == 'examples'
Requires-Dist: scipy; extra == 'examples'
Requires-Dist: trimesh>=4.6.8; extra == 'examples'
Requires-Dist: usd-core>=25.5; (platform_machine != 'aarch64') and extra == 'examples'
Requires-Dist: usd-exchange>=2.1.0a3; (platform_machine == 'aarch64') and extra == 'examples'
Provides-Extra: importers
Requires-Dist: alphashape>=1.3.1; extra == 'importers'
Requires-Dist: coacd>=1.0.7; extra == 'importers'
Requires-Dist: fast-simplification>=0.1.11; extra == 'importers'
Requires-Dist: pycollada>=0.9; extra == 'importers'
Requires-Dist: scipy; extra == 'importers'
Requires-Dist: trimesh>=4.6.8; extra == 'importers'
Requires-Dist: usd-core>=25.5; (platform_machine != 'aarch64') and extra == 'importers'
Requires-Dist: usd-exchange>=2.1.0a3; (platform_machine == 'aarch64') and extra == 'importers'
Provides-Extra: sim
Requires-Dist: cbor2>=5.7.0; extra == 'sim'
Requires-Dist: mujoco-warp>=0.0.1; extra == 'sim'
Requires-Dist: mujoco>=3.3.3.dev769049331; extra == 'sim'
Provides-Extra: torch-cu12
Requires-Dist: alphashape>=1.3.1; extra == 'torch-cu12'
Requires-Dist: cbor2>=5.7.0; extra == 'torch-cu12'
Requires-Dist: coacd>=1.0.7; extra == 'torch-cu12'
Requires-Dist: fast-simplification>=0.1.11; extra == 'torch-cu12'
Requires-Dist: gitpython>=3.1.44; extra == 'torch-cu12'
Requires-Dist: imgui-bundle>=1.92.0; extra == 'torch-cu12'
Requires-Dist: mujoco-warp>=0.0.1; extra == 'torch-cu12'
Requires-Dist: mujoco>=3.3.3.dev769049331; extra == 'torch-cu12'
Requires-Dist: pycollada>=0.9; extra == 'torch-cu12'
Requires-Dist: pyglet>=2.1.6; extra == 'torch-cu12'
Requires-Dist: pyyaml>=6.0.2; extra == 'torch-cu12'
Requires-Dist: scipy; extra == 'torch-cu12'
Requires-Dist: torch>=2.7.0; extra == 'torch-cu12'
Requires-Dist: trimesh>=4.6.8; extra == 'torch-cu12'
Requires-Dist: usd-core>=25.5; (platform_machine != 'aarch64') and extra == 'torch-cu12'
Requires-Dist: usd-exchange>=2.1.0a3; (platform_machine == 'aarch64') and extra == 'torch-cu12'
